extract_layers.py
extract_layers-1.0.1.dist-info/LICENSE
extract_layers-1.0.1.dist-info/METADATA
extract_layers-1.0.1.dist-info/WHEEL
extract_layers-1.0.1.dist-info/entry_points.txt
extract_layers-1.0.1.dist-info/top_level.txt
extract_layers-1.0.1.dist-info/RECORD
